awslabs/__init__.py
awslabs/ecs_mcp_server/__init__.py
awslabs/ecs_mcp_server/main.py
awslabs/ecs_mcp_server/api/__init__.py
awslabs/ecs_mcp_server/api/containerize.py
awslabs/ecs_mcp_server/api/delete.py
awslabs/ecs_mcp_server/api/ecs_troubleshooting.py
awslabs/ecs_mcp_server/api/express.py
awslabs/ecs_mcp_server/api/infrastructure.py
awslabs/ecs_mcp_server/api/resource_management.py
awslabs/ecs_mcp_server/api/status.py
awslabs/ecs_mcp_server/api/troubleshooting_tools/__init__.py
awslabs/ecs_mcp_server/api/troubleshooting_tools/detect_image_pull_failures.py
awslabs/ecs_mcp_server/api/troubleshooting_tools/fetch_cloudformation_status.py
awslabs/ecs_mcp_server/api/troubleshooting_tools/fetch_network_configuration.py
awslabs/ecs_mcp_server/api/troubleshooting_tools/fetch_service_events.py
awslabs/ecs_mcp_server/api/troubleshooting_tools/fetch_task_failures.py
awslabs/ecs_mcp_server/api/troubleshooting_tools/fetch_task_logs.py
awslabs/ecs_mcp_server/api/troubleshooting_tools/get_ecs_troubleshooting_guidance.py
awslabs/ecs_mcp_server/api/troubleshooting_tools/utils.py
awslabs/ecs_mcp_server/modules/__init__.py
awslabs/ecs_mcp_server/modules/aws_knowledge_proxy.py
awslabs/ecs_mcp_server/modules/containerize.py
awslabs/ecs_mcp_server/modules/delete.py
awslabs/ecs_mcp_server/modules/deployment_status.py
awslabs/ecs_mcp_server/modules/express.py
awslabs/ecs_mcp_server/modules/infrastructure.py
awslabs/ecs_mcp_server/modules/resource_management.py
awslabs/ecs_mcp_server/modules/troubleshooting.py
awslabs/ecs_mcp_server/templates/ecr_infrastructure.json
awslabs/ecs_mcp_server/templates/ecs_infrastructure.json
awslabs/ecs_mcp_server/utils/arn_parser.py
awslabs/ecs_mcp_server/utils/aws.py
awslabs/ecs_mcp_server/utils/config.py
awslabs/ecs_mcp_server/utils/docker.py
awslabs/ecs_mcp_server/utils/security.py
awslabs/ecs_mcp_server/utils/templates.py
awslabs/ecs_mcp_server/utils/time_utils.py
awslabs_ecs_mcp_server-0.1.24.dist-info/METADATA
awslabs_ecs_mcp_server-0.1.24.dist-info/WHEEL
awslabs_ecs_mcp_server-0.1.24.dist-info/entry_points.txt
awslabs_ecs_mcp_server-0.1.24.dist-info/RECORD
